conekta/__init__.py
conekta/api_client.py
conekta/api_response.py
conekta/configuration.py
conekta/exceptions.py
conekta/py.typed
conekta/rest.py
conekta/api/__init__.py
conekta/api/antifraud_api.py
conekta/api/api_keys_api.py
conekta/api/balances_api.py
conekta/api/charges_api.py
conekta/api/companies_api.py
conekta/api/customers_api.py
conekta/api/discounts_api.py
conekta/api/events_api.py
conekta/api/logs_api.py
conekta/api/orders_api.py
conekta/api/payment_link_api.py
conekta/api/payment_methods_api.py
conekta/api/payout_orders_api.py
conekta/api/plans_api.py
conekta/api/products_api.py
conekta/api/shipping_contacts_api.py
conekta/api/shippings_api.py
conekta/api/subscriptions_api.py
conekta/api/taxes_api.py
conekta/api/tokens_api.py
conekta/api/transactions_api.py
conekta/api/transfers_api.py
conekta/api/webhook_keys_api.py
conekta/api/webhooks_api.py
conekta/models/__init__.py
conekta/models/api_key_create_response.py
conekta/models/api_key_request.py
conekta/models/api_key_response.py
conekta/models/api_key_response_on_delete.py
conekta/models/api_key_update_request.py
conekta/models/balance_common_field.py
conekta/models/balance_response.py
conekta/models/blacklist_rule_response.py
conekta/models/charge_order_response.py
conekta/models/charge_order_response_payment_method.py
conekta/models/charge_request.py
conekta/models/charge_request_payment_method.py
conekta/models/charge_response.py
conekta/models/charge_response_channel.py
conekta/models/charge_response_payment_method.py
conekta/models/charge_response_refunds.py
conekta/models/charge_response_refunds_data.py
conekta/models/charge_update_request.py
conekta/models/charges_data_response.py
conekta/models/charges_order_response.py
conekta/models/charges_order_response_all_of_data.py
conekta/models/checkout.py
conekta/models/checkout_order_template.py
conekta/models/checkout_order_template_customer_info.py
conekta/models/checkout_request.py
conekta/models/checkout_response.py
conekta-7.0.3.dist-info/licenses/AUTHORS.md
conekta-7.0.3.dist-info/licenses/LICENSE
conekta-7.0.3.dist-info/METADATA
conekta-7.0.3.dist-info/WHEEL
conekta-7.0.3.dist-info/top_level.txt
conekta-7.0.3.dist-info/RECORD
