Metadata-Version: 2.4
Name: conekta
Version: 7.0.3
Summary: Conekta API
Home-page: https://github.com/conekta/conekta-python
Author: Engineering Conekta
Author-email: engineering@conekta.com
License: MIT-LICENSE
Keywords: OpenAPI,OpenAPI-Generator,Conekta API
License-File: LICENSE
License-File: AUTHORS.md
Requires-Dist: urllib3<3.0.0,>=1.25.3
Requires-Dist: python-dateutil>=2.8.2
Requires-Dist: pydantic>=2
Requires-Dist: typing-extensions>=4.7.1
Dynamic: author
Dynamic: author-email
Dynamic: description
Dynamic: description-content-type
Dynamic: home-page
Dynamic: keywords
Dynamic: license
Dynamic: license-file
Dynamic: requires-dist
Dynamic: summary
